[
  {
    "house_address": "018/1524",
    "house_name": "Panackalveed",
    "household_id": "018/1524|PA",
    "total_members": 10,
    "voting_power_percentage": 0.77,
    "head_of_household": "Ruckiyaumma",
    "household_type": "Multi-Family House",
    "unique_guardians": 6,
    "religious_composition": {
      "Muslim": 7,
      "Hindu": 3
    },
    "members": [
      {
        "serial_no": 1131,
        "name": "Ruckiyaumma",
        "guardian": "Abdulsamad",
        "age": 70,
        "gender": "F",
        "religion": "Muslim",
        "house_name": "Panayckalveed",
        "relationship": "Elder"
      },
      {
        "serial_no": 1132,
        "name": "Rajamma",
        "guardian": "Babu",
        "age": 60,
        "gender": "F",
        "religion": "Hindu",
        "house_name": "Panaykkalthodi",
        "relationship": "Elder"
      },
      {
        "serial_no": 1133,
        "name": "Harid",
        "guardian": "Abdulsamad",
        "age": 45,
        "gender": "M",
        "religion": "Muslim",
        "house_name": "Panayckalveed",
        "relationship": "Adult Member"
      },
      {
        "serial_no": 1134,
        "name": "Thalhath",
        "guardian": "Abdulsamad",
        "age": 45,
        "gender": "M",
        "religion": "Muslim",
        "house_name": "Panackalveedu",
        "relationship": "Head of Family"
      },
      {
        "serial_no": 1135,
        "name": "Sajila",
        "guardian": "Jabin",
        "age": 41,
        "gender": "F",
        "religion": "Muslim",
        "house_name": "Panackalveed",
        "relationship": "Adult Member"
      },
      {
        "serial_no": 1136,
        "name": "Ratheesh",
        "guardian": "Babu",
        "age": 38,
        "gender": "M",
        "religion": "Hindu",
        "house_name": "Parasseri Vadakkathil",
        "relationship": "Adult Member"
      },
      {
        "serial_no": 1137,
        "name": "Shuhaib",
        "guardian": "Abdhulsamad",
        "age": 37,
        "gender": "M",
        "religion": "Muslim",
        "house_name": "Panackalveed",
        "relationship": "Adult Member"
      },
      {
        "serial_no": 1138,
        "name": "Rajalekshmi",
        "guardian": "Babu",
        "age": 36,
        "gender": "F",
        "religion": "Hindu",
        "house_name": "Panaykkal Thodiyil",
        "relationship": "Adult Member"
      },
      {
        "serial_no": 1139,
        "name": "Shahana",
        "guardian": "Thalhath",
        "age": 35,
        "gender": "F",
        "religion": "Muslim",
        "house_name": "Panakkalveedu",
        "relationship": "Adult Member"
      },
      {
        "serial_no": 1140,
        "name": "Fathima J",
        "guardian": "Jabir A",
        "age": 23,
        "gender": "F",
        "religion": "Muslim",
        "house_name": "Panackal Veedu, Venad Nagar 123",
        "relationship": "Young Adult"
      }
    ],
    "strategy": "High-priority personal visit by senior leader | Multiple touchpoints for different families | Secular/inclusive messaging",
    "region": "Low Numbers",
    "region_label": "Low Numbers (0-239672)"
  },
  {
    "house_address": "018/1577",
    "house_name": "Kalayil",
    "household_id": "018/1577|KA",
    "total_members": 9,
    "voting_power_percentage": 0.7,
    "head_of_household": "Sasidharan",
    "household_type": "Multi-Family House",
    "unique_guardians": 7,
    "religious_composition": {
      "Hindu": 9
    },
    "members": [
      {
        "serial_no": 1238,
        "name": "Sasidharan",
        "guardian": "Kumaran",
        "age": 75,
        "gender": "M",
        "religion": "Hindu",
        "house_name": "Kalayil",
        "relationship": "Head of Family"
      },
      {
        "serial_no": 1239,
        "name": "Indira",
        "guardian": "Sasidharan",
        "age": 60,
        "gender": "F",
        "religion": "Hindu",
        "house_name": "Kalayil",
        "relationship": "Elder"
      },
      {
        "serial_no": 1240,
        "name": "Prakas",
        "guardian": "Haridasan",
        "age": 49,
        "gender": "M",
        "religion": "Hindu",
        "house_name": "Kalayil",
        "relationship": "Head of Family"
      },
      {
        "serial_no": 1241,
        "name": "Seetha",
        "guardian": "Prakas",
        "age": 46,
        "gender": "F",
        "religion": "Hindu",
        "house_name": "Kalayil",
        "relationship": "Adult Member"
      },
      {
        "serial_no": 1242,
        "name": "Mithunraj",
        "guardian": "Divyaraj",
        "age": 37,
        "gender": "M",
        "religion": "Hindu",
        "house_name": "Kamalalalayam",
        "relationship": "Adult Member"
      },
      {
        "serial_no": 1243,
        "name": "Syam Sasidharan",
        "guardian": "Sasidharan",
        "age": 36,
        "gender": "M",
        "religion": "Hindu",
        "house_name": "Kalayil",
        "relationship": "Parent"
      },
      {
        "serial_no": 1244,
        "name": "Shamina Syam",
        "guardian": "Syam Sasidharan",
        "age": 35,
        "gender": "F",
        "religion": "Hindu",
        "house_name": "Kalayil",
        "relationship": "Adult Member"
      },
      {
        "serial_no": 1245,
        "name": "Santhi",
        "guardian": "Prakash",
        "age": 32,
        "gender": "F",
        "religion": "Hindu",
        "house_name": "Kalayil",
        "relationship": "Young Adult"
      },
      {
        "serial_no": 1246,
        "name": "Sarath",
        "guardian": "Prakash",
        "age": 30,
        "gender": "M",
        "religion": "Hindu",
        "house_name": "Kalayil Veedu",
        "relationship": "Young Adult"
      }
    ],
    "strategy": "Personal home visit by campaign team | Multiple touchpoints for different families | Community-specific outreach (Hindu)",
    "region": "Low Numbers",
    "region_label": "Low Numbers (0-239672)"
  },
  {
    "house_address": "018/1526",
    "house_name": "Panayckalpadinjattathil",
    "household_id": "018/1526|PA",
    "total_members": 8,
    "voting_power_percentage": 0.62,
    "head_of_household": "Nebeesabivi",
    "household_type": "Multi-Family House",
    "unique_guardians": 5,
    "religious_composition": {
      "Muslim": 8
    },
    "members": [
      {
        "serial_no": 1143,
        "name": "Nebeesabivi",
        "guardian": "Abdulkhadar",
        "age": 77,
        "gender": "F",
        "religion": "Muslim",
        "house_name": "Panayckalpadinjattathil",
        "relationship": "Elder"
      },
      {
        "serial_no": 1144,
        "name": "Noushad",
        "guardian": "Muhammad Kunj",
        "age": 56,
        "gender": "M",
        "religion": "Muslim",
        "house_name": "Panayckalpadinjattathil",
        "relationship": "Head of Family"
      },
      {
        "serial_no": 1145,
        "name": "Thahira",
        "guardian": "Noushad",
        "age": 49,
        "gender": "F",
        "religion": "Muslim",
        "house_name": "Panayckalpadinjattathil",
        "relationship": "Adult Member"
      },
      {
        "serial_no": 1146,
        "name": "Noushad",
        "guardian": "Abdulkhadar",
        "age": 48,
        "gender": "M",
        "religion": "Muslim",
        "house_name": "Panayckalpadinjattathil",
        "relationship": "Head of Family"
      },
      {
        "serial_no": 1147,
        "name": "Rahumathu Beevi",
        "guardian": "Noushad",
        "age": 44,
        "gender": "F",
        "religion": "Muslim",
        "house_name": "Panakalpadinjattathil",
        "relationship": "Adult Member"
      },
      {
        "serial_no": 1148,
        "name": "Ramla",
        "guardian": "Noushad",
        "age": 37,
        "gender": "F",
        "religion": "Muslim",
        "house_name": "Panackalpadinjattathil",
        "relationship": "Adult Member"
      },
      {
        "serial_no": 1149,
        "name": "Shaila",
        "guardian": "Hashim",
        "age": 37,
        "gender": "F",
        "religion": "Muslim",
        "house_name": "Panayckalpadinjattathil",
        "relationship": "Adult Member"
      },
      {
        "serial_no": 1150,
        "name": "Nejumudeen",
        "guardian": "Abdulsalim",
        "age": 34,
        "gender": "M",
        "religion": "Muslim",
        "house_name": "Panakkalpadinjattathil",
        "relationship": "Young Adult"
      }
    ],
    "strategy": "Personal home visit by campaign team | Multiple touchpoints for different families | Community-specific outreach (Muslim)",
    "region": "Low Numbers",
    "region_label": "Low Numbers (0-239672)"
  },
  {
    "house_address": "018/1527",
    "house_name": "Panackalpadinjattathi",
    "household_id": "018/1527|PA",
    "total_members": 7,
    "voting_power_percentage": 0.54,
    "head_of_household": "Thaha",
    "household_type": "Multi-Family House",
    "unique_guardians": 3,
    "religious_composition": {
      "Muslim": 7
    },
    "members": [
      {
        "serial_no": 1151,
        "name": "Thaha",
        "guardian": "Sahidkunj",
        "age": 50,
        "gender": "M",
        "religion": "Muslim",
        "house_name": "Panayckalpadinjattathil",
        "relationship": "Head of Family"
      },
      {
        "serial_no": 1152,
        "name": "Thajudeen",
        "guardian": "Kabeer",
        "age": 46,
        "gender": "M",
        "religion": "Muslim",
        "house_name": "Panayckalpadinjattathil",
        "relationship": "Adult Member"
      },
      {
        "serial_no": 1153,
        "name": "Asurabeevi",
        "guardian": "Thaha",
        "age": 43,
        "gender": "F",
        "religion": "Muslim",
        "house_name": "Panayckalpadinjattathil",
        "relationship": "Adult Member"
      },
      {
        "serial_no": 1154,
        "name": "Basheer",
        "guardian": "Kabeer",
        "age": 41,
        "gender": "M",
        "religion": "Muslim",
        "house_name": "Panackalpadinjattathi",
        "relationship": "Adult Member"
      },
      {
        "serial_no": 1155,
        "name": "Sofiya",
        "guardian": "Kabeer",
        "age": 41,
        "gender": "F",
        "religion": "Muslim",
        "house_name": "Panackalpadinjattathi",
        "relationship": "Adult Member"
      },
      {
        "serial_no": 1156,
        "name": "Sooryath",
        "guardian": "Kabeer",
        "age": 37,
        "gender": "F",
        "religion": "Muslim",
        "house_name": "Panackalpadinjattathi",
        "relationship": "Adult Member"
      },
      {
        "serial_no": 1157,
        "name": "Haseena",
        "guardian": "Thaha",
        "age": 29,
        "gender": "F",
        "religion": "Muslim",
        "house_name": "Panakkal Padinjattathil",
        "relationship": "Young Adult"
      }
    ],
    "strategy": "Personal home visit by campaign team | Multiple touchpoints for different families | Community-specific outreach (Muslim)",
    "region": "Low Numbers",
    "region_label": "Low Numbers (0-239672)"
  },
  {
    "house_address": "018/1442",
    "house_name": "Plavilazhikathuthodi",
    "household_id": "018/1442|PL",
    "total_members": 7,
    "voting_power_percentage": 0.54,
    "head_of_household": "Sarojini",
    "household_type": "Multi-Family House",
    "unique_guardians": 5,
    "religious_composition": {
      "Hindu": 7
    },
    "members": [
      {
        "serial_no": 942,
        "name": "Sarojini",
        "guardian": "Nanu",
        "age": 72,
        "gender": "F",
        "religion": "Hindu",
        "house_name": "Plavilazhikathuthodi",
        "relationship": "Head of Family"
      },
      {
        "serial_no": 943,
        "name": "Raveendran",
        "guardian": "Sadanandan",
        "age": 52,
        "gender": "M",
        "religion": "Hindu",
        "house_name": "Plavilazhikathuthodi",
        "relationship": "Head of Family"
      },
      {
        "serial_no": 944,
        "name": "Sindhu",
        "guardian": "Raveendran",
        "age": 48,
        "gender": "F",
        "religion": "Hindu",
        "house_name": "Plavilazhikathuthodi",
        "relationship": "Adult Member"
      },
      {
        "serial_no": 947,
        "name": "VINOD K",
        "guardian": "MINIMOL",
        "age": 44,
        "gender": "M",
        "religion": "Hindu",
        "house_name": "PLAVILAZHIKATHU THODIYIL",
        "relationship": "Adult Member"
      },
      {
        "serial_no": 948,
        "name": "Minimol",
        "guardian": "Nanu",
        "age": 43,
        "gender": "F",
        "religion": "Hindu",
        "house_name": "Plavilazhikathuthodi",
        "relationship": "Adult Member"
      },
      {
        "serial_no": 949,
        "name": "Sunil Kumar",
        "guardian": "Sarojini",
        "age": 42,
        "gender": "M",
        "religion": "Hindu",
        "house_name": "Plavilazhikath Veedu",
        "relationship": "Adult Member"
      },
      {
        "serial_no": 950,
        "name": "Renjith",
        "guardian": "Raveendran",
        "age": 33,
        "gender": "M",
        "religion": "Hindu",
        "house_name": "plavilazhikathu Thodiyil",
        "relationship": "Young Adult"
      }
    ],
    "strategy": "Personal home visit by campaign team | Multiple touchpoints for different families | Community-specific outreach (Hindu)",
    "region": "Low Numbers",
    "region_label": "Low Numbers (0-239672)"
  },
  {
    "house_address": "018/1428",
    "house_name": "Plavilazhikathuthodi",
    "household_id": "018/1428|PL",
    "total_members": 7,
    "voting_power_percentage": 0.54,
    "head_of_household": "Balakrishnan",
    "household_type": "Multi-Family House",
    "unique_guardians": 5,
    "religious_composition": {
      "Hindu": 7
    },
    "members": [
      {
        "serial_no": 908,
        "name": "Balakrishnan",
        "guardian": "Narayanan",
        "age": 69,
        "gender": "M",
        "religion": "Hindu",
        "house_name": "Plavilazhikathu Thackethodiyil",
        "relationship": "Elder"
      },
      {
        "serial_no": 909,
        "name": "Rajan",
        "guardian": "Velayudhan",
        "age": 62,
        "gender": "M",
        "religion": "Hindu",
        "house_name": "Plavilazhikathuthodi",
        "relationship": "Head of Family"
      },
      {
        "serial_no": 910,
        "name": "Lalitha",
        "guardian": "Rajan",
        "age": 60,
        "gender": "F",
        "religion": "Hindu",
        "house_name": "Plavilazhikathuthodi",
        "relationship": "Elder"
      },
      {
        "serial_no": 911,
        "name": "Geetha",
        "guardian": "Sundaran",
        "age": 52,
        "gender": "F",
        "religion": "Hindu",
        "house_name": "Plavilazhikath Thacke Thodiyil",
        "relationship": "Adult Member"
      },
      {
        "serial_no": 912,
        "name": "Rajeev",
        "guardian": "Rajan",
        "age": 36,
        "gender": "M",
        "religion": "Hindu",
        "house_name": "Plavilazhikaththackethodiyil",
        "relationship": "Adult Member"
      },
      {
        "serial_no": 913,
        "name": "Remya",
        "guardian": "Rajan",
        "age": 35,
        "gender": "F",
        "religion": "Hindu",
        "house_name": "Plavilazhikathuthodi",
        "relationship": "Adult Member"
      },
      {
        "serial_no": 914,
        "name": "GEETHU SUNDER G S",
        "guardian": "SUNDERAN",
        "age": 25,
        "gender": "F",
        "religion": "Hindu",
        "house_name": "PLAVILAZHIKATH THEKKE THODIYIL",
        "relationship": "Young Adult"
      }
    ],
    "strategy": "Personal home visit by campaign team | Multiple touchpoints for different families | Community-specific outreach (Hindu)",
    "region": "Low Numbers",
    "region_label": "Low Numbers (0-239672)"
  },
  {
    "house_address": "018/1190",
    "house_name": "Parasseri Thekkathil Venad Nagar 97",
    "household_id": "018/1190|PA",
    "total_members": 7,
    "voting_power_percentage": 0.54,
    "head_of_household": "Abdul Salam",
    "household_type": "Multi-Family House",
    "unique_guardians": 3,
    "religious_composition": {
      "Muslim": 7
    },
    "members": [
      {
        "serial_no": 802,
        "name": "Abdul Salam",
        "guardian": "Alikunju",
        "age": 69,
        "gender": "M",
        "religion": "Muslim",
        "house_name": "Parasseri Thekkathil Venad Nagar 97",
        "relationship": "Head of Family"
      },
      {
        "serial_no": 803,
        "name": "Shahubanath",
        "guardian": "Abdul Salam",
        "age": 62,
        "gender": "F",
        "religion": "Muslim",
        "house_name": "Parasseri Thekkathil Venad Nagar 97",
        "relationship": "Elder"
      },
      {
        "serial_no": 804,
        "name": "Faisal P",
        "guardian": "Alikunju",
        "age": 44,
        "gender": "M",
        "religion": "Muslim",
        "house_name": "Parasseri Thekkathil Kannimel Cherry",
        "relationship": "Adult Member"
      },
      {
        "serial_no": 805,
        "name": "Shanavas A",
        "guardian": "Abdul Salam",
        "age": 44,
        "gender": "M",
        "religion": "Muslim",
        "house_name": "Parasseri Thekkathil Venad Nagar 97",
        "relationship": "Adult Member"
      },
      {
        "serial_no": 806,
        "name": "Shamila S",
        "guardian": "Faizal",
        "age": 42,
        "gender": "F",
        "religion": "Muslim",
        "house_name": "Parasseri Thekkathil Venad Nagar 97",
        "relationship": "Adult Member"
      },
      {
        "serial_no": 807,
        "name": "Shajahan A",
        "guardian": "Abdul Salam",
        "age": 40,
        "gender": "M",
        "religion": "Muslim",
        "house_name": "Parasseri Thekkathil Kannimel Chery",
        "relationship": "Adult Member"
      },
      {
        "serial_no": 808,
        "name": "Shahina Faizal",
        "guardian": "Faizal",
        "age": 20,
        "gender": "F",
        "religion": "Muslim",
        "house_name": "Parasseri Thekkathil Venad Nagar97",
        "relationship": "Young Adult"
      }
    ],
    "strategy": "Personal home visit by campaign team | Multiple touchpoints for different families | Community-specific outreach (Muslim)",
    "region": "Low Numbers",
    "region_label": "Low Numbers (0-239672)"
  },
  {
    "house_address": "018/1402",
    "house_name": "Thailazhikathu veedu",
    "household_id": "018/1402|TH",
    "total_members": 7,
    "voting_power_percentage": 0.54,
    "head_of_household": "Leelamma",
    "household_type": "Multi-Family House",
    "unique_guardians": 5,
    "religious_composition": {
      "Hindu": 7
    },
    "members": [
      {
        "serial_no": 866,
        "name": "Leelamma",
        "guardian": "Chandranpilla",
        "age": 64,
        "gender": "F",
        "religion": "Hindu",
        "house_name": "Thayyalazhikathuveed",
        "relationship": "Elder"
      },
      {
        "serial_no": 867,
        "name": "Karmmachandran",
        "guardian": "Bhaskaran Pilla",
        "age": 52,
        "gender": "M",
        "religion": "Hindu",
        "house_name": "Thayyilazhikath",
        "relationship": "Adult Member"
      },
      {
        "serial_no": 868,
        "name": "Sunitha",
        "guardian": "Raghavanpilla",
        "age": 45,
        "gender": "F",
        "religion": "Hindu",
        "house_name": "Thayyalazhikathveed",
        "relationship": "Adult Member"
      },
      {
        "serial_no": 869,
        "name": "Arun Chand",
        "guardian": "Chandranpilla",
        "age": 36,
        "gender": "M",
        "religion": "Hindu",
        "house_name": "Thayyalazhikathuveed",
        "relationship": "Adult Member"
      },
      {
        "serial_no": 870,
        "name": "Arunima",
        "guardian": "Chandranpilla",
        "age": 33,
        "gender": "F",
        "religion": "Hindu",
        "house_name": "Thailetha Veed",
        "relationship": "Young Adult"
      },
      {
        "serial_no": 871,
        "name": "Mekhana",
        "guardian": "Karma chandran. B",
        "age": 23,
        "gender": "F",
        "religion": "Hindu",
        "house_name": "Thailazhikathu veedu",
        "relationship": "Young Adult"
      },
      {
        "serial_no": 872,
        "name": "Keerthana. S",
        "guardian": "Karma chandran.B",
        "age": 21,
        "gender": "F",
        "religion": "Hindu",
        "house_name": "Thailazhikathu veedu",
        "relationship": "Young Adult"
      }
    ],
    "strategy": "Personal home visit by campaign team | Multiple touchpoints for different families | Community-specific outreach (Hindu)",
    "region": "Low Numbers",
    "region_label": "Low Numbers (0-239672)"
  },
  {
    "house_address": "018/955",
    "house_name": "Vayalilputhanveed",
    "household_id": "018/955|VA",
    "total_members": 6,
    "voting_power_percentage": 0.46,
    "head_of_household": "Anandavalli",
    "household_type": "Extended Family",
    "unique_guardians": 2,
    "religious_composition": {
      "Hindu": 6
    },
    "members": [
      {
        "serial_no": 493,
        "name": "Anandavalli",
        "guardian": "Surendran",
        "age": 55,
        "gender": "F",
        "religion": "Hindu",
        "house_name": "Vayalilputhanveed",
        "relationship": "Adult Member"
      },
      {
        "serial_no": 494,
        "name": "Maniyamma",
        "guardian": "Surendran",
        "age": 48,
        "gender": "F",
        "religion": "Hindu",
        "house_name": "Vayalilputhanveed",
        "relationship": "Adult Member"
      },
      {
        "serial_no": 495,
        "name": "Suresh",
        "guardian": "Surendran",
        "age": 42,
        "gender": "M",
        "religion": "Hindu",
        "house_name": "Valilputhanveed",
        "relationship": "Adult Member"
      },
      {
        "serial_no": 496,
        "name": "Sunil",
        "guardian": "Surendran",
        "age": 36,
        "gender": "M",
        "religion": "Hindu",
        "house_name": "Vayalilputhanveed",
        "relationship": "Adult Member"
      },
      {
        "serial_no": 497,
        "name": "Santhosh",
        "guardian": "Surendran",
        "age": 36,
        "gender": "M",
        "religion": "Hindu",
        "house_name": "Vayalilputhanveed",
        "relationship": "Parent"
      },
      {
        "serial_no": 498,
        "name": "Preetha",
        "guardian": "Santhosh",
        "age": 32,
        "gender": "F",
        "religion": "Hindu",
        "house_name": "Vayalilputhenveedu",
        "relationship": "Young Adult"
      }
    ],
    "strategy": "Personal home visit by campaign team | Focus on family head/eldest member | Community-specific outreach (Hindu)",
    "region": "Low Numbers",
    "region_label": "Low Numbers (0-239672)"
  },
  {
    "house_address": "018/1550",
    "house_name": "Paraserikizhackathil",
    "household_id": "018/1550|PA",
    "total_members": 6,
    "voting_power_percentage": 0.46,
    "head_of_household": "Raveendran",
    "household_type": "Extended Family",
    "unique_guardians": 6,
    "religious_composition": {
      "Hindu": 6
    },
    "members": [
      {
        "serial_no": 1190,
        "name": "Raveendran",
        "guardian": "Velayudhan",
        "age": 84,
        "gender": "M",
        "religion": "Hindu",
        "house_name": "Paraserithackathil",
        "relationship": "Elder"
      },
      {
        "serial_no": 1191,
        "name": "Radhamani",
        "guardian": "Thankappanpilala",
        "age": 65,
        "gender": "F",
        "religion": "Hindu",
        "house_name": "Panackalveed",
        "relationship": "Elder"
      },
      {
        "serial_no": 1192,
        "name": "Raju",
        "guardian": "Kumaran",
        "age": 53,
        "gender": "M",
        "religion": "Hindu",
        "house_name": "Paraserikizhackathil",
        "relationship": "Head of Family"
      },
      {
        "serial_no": 1193,
        "name": "Sulekha",
        "guardian": "Raju",
        "age": 50,
        "gender": "F",
        "religion": "Hindu",
        "house_name": "Paraserikizhackathil",
        "relationship": "Adult Member"
      },
      {
        "serial_no": 1194,
        "name": "Jyathilakshmi",
        "guardian": "Thankappan Pilla",
        "age": 40,
        "gender": "F",
        "religion": "Hindu",
        "house_name": "Panackal Veed",
        "relationship": "Adult Member"
      },
      {
        "serial_no": 1195,
        "name": "Haritha",
        "guardian": "Rajendran",
        "age": 29,
        "gender": "F",
        "religion": "Hindu",
        "house_name": "Panackal Veedu",
        "relationship": "Young Adult"
      }
    ],
    "strategy": "Personal home visit by campaign team | Focus on family head/eldest member | Community-specific outreach (Hindu)",
    "region": "Low Numbers",
    "region_label": "Low Numbers (0-239672)"
  }
]